pyScaf.py
pyScaf-0.12a4.dist-info/DESCRIPTION.rst
pyScaf-0.12a4.dist-info/METADATA
pyScaf-0.12a4.dist-info/RECORD
pyScaf-0.12a4.dist-info/WHEEL
pyScaf-0.12a4.dist-info/entry_points.txt
pyScaf-0.12a4.dist-info/metadata.json
pyScaf-0.12a4.dist-info/top_level.txt
