Metadata-Version: 2.0
Name: pyScaf
Version: 0.12a4
Summary: UNKNOWN
Home-page: https://github.com/lpryszcz/pyScaf
Author: Leszek Pryszcz
Author-email: l.p.pryszcz+distutils@gmail.com
License: GPLv3
Keywords: assembly scaffolding paired-end long-reads synteny
Platform: UNKNOWN
Classifier: Development Status :: 4 - Beta
Classifier: Programming Language :: Python :: 2
Classifier: Programming Language :: Python :: 2.7
Requires-Dist: FastaIndex
